textacy/__init__.py
textacy/__main__.py
textacy/_version.py
textacy/cache.py
textacy/constants.py
textacy/corpus.py
textacy/errors.py
textacy/py.typed
textacy/types.py
textacy/utils.py
textacy/augmentation/__init__.py
textacy/augmentation/augmenter.py
textacy/augmentation/transforms.py
textacy/augmentation/utils.py
textacy/datasets/__init__.py
textacy/datasets/base.py
textacy/datasets/capitol_words.py
textacy/datasets/imdb.py
textacy/datasets/oxford_text_archive.py
textacy/datasets/reddit_comments.py
textacy/datasets/supreme_court.py
textacy/datasets/udhr.py
textacy/datasets/wikimedia.py
textacy/extract/__init__.py
textacy/extract/_exts.py
textacy/extract/acros.py
textacy/extract/bags.py
textacy/extract/basics.py
textacy/extract/kwic.py
textacy/extract/matches.py
textacy/extract/triples.py
textacy/extract/utils.py
textacy/extract/keyterms/__init__.py
textacy/extract/keyterms/scake.py
textacy/extract/keyterms/sgrank.py
textacy/extract/keyterms/textrank.py
textacy/extract/keyterms/yake.py
textacy/io/__init__.py
textacy/io/csv.py
textacy/io/http.py
textacy/io/json.py
textacy/io/matrix.py
textacy/io/spacy.py
textacy/io/text.py
textacy/io/utils.py
textacy/lang_id/__init__.py
textacy/lang_id/_datasets.py
textacy/lang_id/_training.py
textacy/lang_id/lang_identifier.py
textacy/lang_id/models.py
textacy/preprocessing/__init__.py
textacy/preprocessing/normalize.py
textacy/preprocessing/pipeline.py
textacy/preprocessing/remove.py
textacy/preprocessing/replace.py
textacy/preprocessing/resources.py
textacy/representations/__init__.py
textacy/representations/matrix_utils.py
textacy/representations/network.py
textacy/representations/sparse_vec.py
textacy/representations/vectorizers.py
textacy/resources/__init__.py
textacy/resources/base.py
textacy/resources/concept_net.py
textacy/resources/depeche_mood.py
textacy/similarity/__init__.py
textacy/similarity/edits.py
textacy/similarity/hybrid.py
textacy/similarity/sequences.py
textacy/similarity/tokens.py
textacy/spacier/__init__.py
textacy-0.13.0.dist-info/LICENSE.txt
textacy-0.13.0.dist-info/METADATA
textacy-0.13.0.dist-info/WHEEL
textacy-0.13.0.dist-info/top_level.txt
textacy-0.13.0.dist-info/RECORD
