Metadata-Version: 2.1
Name: textacy
Version: 0.13.0
Summary: NLP, before and after spaCy
Maintainer-email: Burton DeWilde <burtdewilde@gmail.com>
License: Copyright 2016 Chartbeat, Inc.
Project-URL: Docs, https://textacy.readthedocs.io
Project-URL: Repo, https://github.com/chartbeat-labs/textacy
Project-URL: Changelog, https://github.com/chartbeat-labs/textacy/blob/main/CHANGES.md
Keywords: spacy,nlp,text processing,linguistics
Classifier: Development Status :: 4 - Beta
Classifier: License :: OSI Approved :: Apache Software License
Classifier: Intended Audience :: Developers
Classifier: Intended Audience :: Science/Research
Classifier: Programming Language :: Python
Classifier: Programming Language :: Python :: 3
Classifier: Programming Language :: Python :: 3.9
Classifier: Programming Language :: Python :: 3.10
Classifier: Programming Language :: Python :: 3.11
Classifier: Natural Language :: English
Classifier: Topic :: Text Processing :: Linguistic
Requires-Python: >=3.9
Provides-Extra: viz
Provides-Extra: dev
Provides-Extra: check
Provides-Extra: docs
License-File: LICENSE.txt
